Workbook

Sheet Total
A1: year | B1: inflation | C1: risk_free_rate | D1: premium_forecast | E1: loss_forecast | F1: operating_expenses | G1: operating_income | H1: net_income | I1: discount_factor | J1: pv_premium | K1: pv_loss | L1: pv_expense | M1: pv_net_income
A2: 2175 | B2: 0.022825428 | C2: 0.048526873 | D2: =SUM(BI!D20+CL_no_gold_plat!D28+EF!D2+WC!D22)/1000000 -> 2.4954336e-08 | E2: =SUM(BI!E20+CL_no_gold_plat!E28+EF!E2+WC!E22)/1000000 -> 2.5685141e-08 | F2: =SUM(BI!F20+CL_no_gold_plat!F28+EF!F2+WC!F22)/1000000 -> 2.5714643e-08 | G2: =SUM(BI!G20+CL_no_gold_plat!G28+EF!G2+WC!G22)/1000000 -> 2.5385925e-08 | H2: =SUM(BI!H20+CL_no_gold_plat!H28+EF!H2+WC!H22)/1000000 -> 2.5078383e-08 | I2: =SUM(BI!I20+CL_no_gold_plat!I28+EF!I2+WC!I22)/1000000 -> 2.4963757e-08 | J2: =SUM(BI!J20+CL_no_gold_plat!J28+EF!J2+WC!J22)/1000000 -> 2.501092e-08 | K2: =SUM(BI!K20+CL_no_gold_plat!K28+EF!K2+WC!K22)/1000000 -> 2.5108676e-08 | ... M2: =SUM(BI!M20+CL_no_gold_plat!M28+EF!M2+WC!M22)/1000000 -> 0
A3: 2176 | B3: 0.023673261 | C3: 0.041959693 | D3: =SUM(BI!D21+CL_no_gold_plat!D29+EF!D3+WC!D23)/1000000 -> 3.8102759e-08 | E3: =SUM(BI!E21+CL_no_gold_plat!E29+EF!E3+WC!E23)/1000000 -> 3.5837566e-08 | F3: =SUM(BI!F21+CL_no_gold_plat!F29+EF!F3+WC!F23)/1000000 -> 3.4507207e-08 | G3: =SUM(BI!G21+CL_no_gold_plat!G29+EF!G3+WC!G23)/1000000 -> 3.3725882e-08 | H3: =SUM(BI!H21+CL_no_gold_plat!H29+EF!H3+WC!H23)/1000000 -> 3.3267006e-08 | I3: =SUM(BI!I21+CL_no_gold_plat!I29+EF!I3+WC!I23)/1000000 -> 3.2997507e-08 | J3: =SUM(BI!J21+CL_no_gold_plat!J29+EF!J3+WC!J23)/1000000 -> 3.2839228e-08 | K3: =SUM(BI!K21+CL_no_gold_plat!K29+EF!K3+WC!K23)/1000000 -> 3.2746271e-08 | ... M3: =SUM(BI!M21+CL_no_gold_plat!M29+EF!M3+WC!M23)/1000000 -> 0
A4: 2177 | B4: 0.024954336 | C4: 0.038102759 | D4: =SUM(BI!D22+CL_no_gold_plat!D30+EF!D4+WC!D24)/1000000 -> 451.53749 | E4: =SUM(BI!E22+CL_no_gold_plat!E30+EF!E4+WC!E24)/1000000 -> 463.1353 | F4: =SUM(BI!F22+CL_no_gold_plat!F30+EF!F4+WC!F24)/1000000 -> 475.04466 | G4: =SUM(BI!G22+CL_no_gold_plat!G30+EF!G4+WC!G24)/1000000 -> 487.1041 | H4: =SUM(BI!H22+CL_no_gold_plat!H30+EF!H4+WC!H24)/1000000 -> 499.31989 | I4: =SUM(BI!I22+CL_no_gold_plat!I30+EF!I4+WC!I24)/1000000 -> 511.78479 | J4: =SUM(BI!J22+CL_no_gold_plat!J30+EF!J4+WC!J24)/1000000 -> 524.585 | K4: =SUM(BI!K22+CL_no_gold_plat!K30+EF!K4+WC!K24)/1000000 -> 537.75663 | ... M4: =SUM(BI!M22+CL_no_gold_plat!M30+EF!M4+WC!M24)/1000000 -> 0
A5: 2178 | B5: 0.025685141 | C5: 0.035837566 | D5: =SUM(BI!D23+CL_no_gold_plat!D31+EF!D5+WC!D25)/1000000 -> 272.39229 | E5: =SUM(BI!E23+CL_no_gold_plat!E31+EF!E5+WC!E25)/1000000 -> 279.38872 | F5: =SUM(BI!F23+CL_no_gold_plat!F31+EF!F5+WC!F25)/1000000 -> 286.57311 | G5: =SUM(BI!G23+CL_no_gold_plat!G31+EF!G5+WC!G25)/1000000 -> 293.84803 | H5: =SUM(BI!H23+CL_no_gold_plat!H31+EF!H5+WC!H25)/1000000 -> 301.21726 | I5: =SUM(BI!I23+CL_no_gold_plat!I31+EF!I5+WC!I25)/1000000 -> 308.73678 | J5: =SUM(BI!J23+CL_no_gold_plat!J31+EF!J5+WC!J25)/1000000 -> 316.45857 | K5: =SUM(BI!K23+CL_no_gold_plat!K31+EF!K5+WC!K25)/1000000 -> 324.40442 | ... M5: =SUM(BI!M23+CL_no_gold_plat!M31+EF!M5+WC!M25)/1000000 -> 0
A6: 2179 | B6: 0.025714643 | C6: 0.034507207 | D6: =SUM(BI!D24+CL_no_gold_plat!D32+EF!D6+WC!D26)/1000000 -> 135.46125 | E6: =SUM(BI!E24+CL_no_gold_plat!E32+EF!E6+WC!E26)/1000000 -> 138.94059 | F6: =SUM(BI!F24+CL_no_gold_plat!F32+EF!F6+WC!F26)/1000000 -> 142.5134 | G6: =SUM(BI!G24+CL_no_gold_plat!G32+EF!G6+WC!G26)/1000000 -> 146.13123 | H6: =SUM(BI!H24+CL_no_gold_plat!H32+EF!H6+WC!H26)/1000000 -> 149.79597 | I6: =SUM(BI!I24+CL_no_gold_plat!I32+EF!I6+WC!I26)/1000000 -> 153.53544 | J6: =SUM(BI!J24+CL_no_gold_plat!J32+EF!J6+WC!J26)/1000000 -> 157.3755 | K6: =SUM(BI!K24+CL_no_gold_plat!K32+EF!K6+WC!K26)/1000000 -> 161.32699 | ... M6: =SUM(BI!M24+CL_no_gold_plat!M32+EF!M6+WC!M26)/1000000 -> 0
A7: 2180 | B7: 0.025385925 | C7: 0.033725882 | D7: =SUM(BI!D25+CL_no_gold_plat!D33+EF!D7+WC!D27)/1000000 -> 131.5063 | E7: =SUM(BI!E25+CL_no_gold_plat!E33+EF!E7+WC!E27)/1000000 -> 134.88406 | F7: =SUM(BI!F25+CL_no_gold_plat!F33+EF!F7+WC!F27)/1000000 -> 138.35255 | G7: =SUM(BI!G25+CL_no_gold_plat!G33+EF!G7+WC!G27)/1000000 -> 141.86476 | H7: =SUM(BI!H25+CL_no_gold_plat!H33+EF!H7+WC!H27)/1000000 -> 145.4225 | I7: =SUM(BI!I25+CL_no_gold_plat!I33+EF!I7+WC!I27)/1000000 -> 149.05279 | J7: =SUM(BI!J25+CL_no_gold_plat!J33+EF!J7+WC!J27)/1000000 -> 152.78074 | K7: =SUM(BI!K25+CL_no_gold_plat!K33+EF!K7+WC!K27)/1000000 -> 156.61686 | ... M7: =SUM(BI!M25+CL_no_gold_plat!M33+EF!M7+WC!M27)/1000000 -> 0
A8: 2181 | B8: 0.025078383 | C8: 0.033267006 | D8: =SUM(BI!D26+CL_no_gold_plat!D34+EF!D8+WC!D28)/1000000 -> 97.445367 | E8: =SUM(BI!E26+CL_no_gold_plat!E34+EF!E8+WC!E28)/1000000 -> 99.948265 | F8: =SUM(BI!F26+CL_no_gold_plat!F34+EF!F8+WC!F28)/1000000 -> 102.5184 | G8: =SUM(BI!G26+CL_no_gold_plat!G34+EF!G8+WC!G28)/1000000 -> 105.12092 | H8: =SUM(BI!H26+CL_no_gold_plat!H34+EF!H8+WC!H28)/1000000 -> 107.75719 | I8: =SUM(BI!I26+CL_no_gold_plat!I34+EF!I8+WC!I28)/1000000 -> 110.44721 | J8: =SUM(BI!J26+CL_no_gold_plat!J34+EF!J8+WC!J28)/1000000 -> 113.2096 | K8: =SUM(BI!K26+CL_no_gold_plat!K34+EF!K8+WC!K28)/1000000 -> 116.05214 | ... M8: =SUM(BI!M26+CL_no_gold_plat!M34+EF!M8+WC!M28)/1000000 -> 0
A9: 2182 | B9: 0.024963757 | C9: 0.032997507 | D9: =SUM(BI!D27+CL_no_gold_plat!D35+EF!D9+WC!D29)/1000000 -> 8.8171691e-07 | E9: =SUM(BI!E27+CL_no_gold_plat!E35+EF!E9+WC!E29)/1000000 -> 8.5121156e-07 | F9: =SUM(BI!F27+CL_no_gold_plat!F35+EF!F9+WC!F29)/1000000 -> 8.2281839e-07 | G9: =SUM(BI!G27+CL_no_gold_plat!G35+EF!G9+WC!G29)/1000000 -> 7.9597349e-07 | H9: =SUM(BI!H27+CL_no_gold_plat!H35+EF!H9+WC!H29)/1000000 -> 7.7034637e-07 | I9: =SUM(BI!I27+CL_no_gold_plat!I35+EF!I9+WC!I29)/1000000 -> 7.4573885e-07 | J9: =SUM(BI!J27+CL_no_gold_plat!J35+EF!J9+WC!J29)/1000000 -> 7.22028e-07 | K9: =SUM(BI!K27+CL_no_gold_plat!K35+EF!K9+WC!K29)/1000000 -> 6.9913397e-07 | ... M9: =SUM(BI!M27+CL_no_gold_plat!M35+EF!M9+WC!M29)/1000000 -> 0
A10: 2183 | B10: 0.02501092 | C10: 0.032839228 | D10: =SUM(BI!D28+CL_no_gold_plat!D36+EF!D10+WC!D30)/1000000 -> 398.12824 | E10: =SUM(BI!E28+CL_no_gold_plat!E36+EF!E10+WC!E30)/1000000 -> 394.22612 | F10: =SUM(BI!F28+CL_no_gold_plat!F36+EF!F10+WC!F30)/1000000 -> 390.87548 | G10: =SUM(BI!G28+CL_no_gold_plat!G36+EF!G10+WC!G30)/1000000 -> 387.72195 | H10: =SUM(BI!H28+CL_no_gold_plat!H36+EF!H10+WC!H30)/1000000 -> 384.64926 | I10: =SUM(BI!I28+CL_no_gold_plat!I36+EF!I10+WC!I30)/1000000 -> 381.6578 | J10: =SUM(BI!J28+CL_no_gold_plat!J36+EF!J10+WC!J30)/1000000 -> 378.76506 | K10: =SUM(BI!K28+CL_no_gold_plat!K36+EF!K10+WC!K30)/1000000 -> 375.96393 | ... M10: =SUM(BI!M28+CL_no_gold_plat!M36+EF!M10+WC!M30)/1000000 -> 0
A11: 2184 | B11: 0.025108676 | C11: 0.032746271 | D11: =SUM(BI!D29+CL_no_gold_plat!D37+EF!D11+WC!D31)/1000000 -> 240.17289 | E11: =SUM(BI!E29+CL_no_gold_plat!E37+EF!E11+WC!E31)/1000000 -> 237.81891 | F11: =SUM(BI!F29+CL_no_gold_plat!F37+EF!F11+WC!F31)/1000000 -> 235.79762 | G11: =SUM(BI!G29+CL_no_gold_plat!G37+EF!G11+WC!G31)/1000000 -> 233.89524 | H11: =SUM(BI!H29+CL_no_gold_plat!H37+EF!H11+WC!H31)/1000000 -> 232.04162 | I11: =SUM(BI!I29+CL_no_gold_plat!I37+EF!I11+WC!I31)/1000000 -> 230.23701 | J11: =SUM(BI!J29+CL_no_gold_plat!J37+EF!J11+WC!J31)/1000000 -> 228.49195 | K11: =SUM(BI!K29+CL_no_gold_plat!K37+EF!K11+WC!K31)/1000000 -> 226.80215 | ... M11: =SUM(BI!M29+CL_no_gold_plat!M37+EF!M11+WC!M31)/1000000 -> 0

Sheet Sheet6
A1: year | B1: 2175 | C1: 2176 | D1: 2177 | E1: 2178 | F1: 2179 | G1: 2180 | H1: 2181 | I1: 2182 | J1: 2183 | K1: 2184
A2: inflation | B2: 0.022825428 | C2: 0.023673261 | D2: 0.024954336 | E2: 0.025685141 | F2: 0.025714643 | G2: 0.025385925 | H2: 0.025078383 | I2: 0.024963757 | J2: 0.02501092 | K2: 0.025108676
A3: risk_free_rate | B3: 0.048526873 | C3: 0.041959693 | D3: 0.038102759 | E3: 0.035837566 | F3: 0.034507207 | G3: 0.033725882 | H3: 0.033267006 | I3: 0.032997507 | J3: 0.032839228 | K3: 0.032746271
A4: premium_forecast | B4: =SUM(BI!B22+CL_no_gold_plat!B30+EF!B4+WC!B24)/1000000 -> 430.35608 | C4: =SUM(BI!C22+CL_no_gold_plat!C30+EF!C4+WC!C24)/1000000 -> 440.54401 | D4: =SUM(BI!D22+CL_no_gold_plat!D30+EF!D4+WC!D24)/1000000 -> 451.53749 | E4: =SUM(BI!E22+CL_no_gold_plat!E30+EF!E4+WC!E24)/1000000 -> 463.1353 | F4: =SUM(BI!F22+CL_no_gold_plat!F30+EF!F4+WC!F24)/1000000 -> 475.04466 | G4: =SUM(BI!G22+CL_no_gold_plat!G30+EF!G4+WC!G24)/1000000 -> 487.1041 | H4: =SUM(BI!H22+CL_no_gold_plat!H30+EF!H4+WC!H24)/1000000 -> 499.31989 | I4: =SUM(BI!I22+CL_no_gold_plat!I30+EF!I4+WC!I24)/1000000 -> 511.78479 | ... K4: =SUM(BI!K22+CL_no_gold_plat!K30+EF!K4+WC!K24)/1000000 -> 537.75663
A5: loss_forecast | B5: =SUM(BI!B23+CL_no_gold_plat!B31+EF!B5+WC!B25)/1000000 -> 259.61449 | C5: =SUM(BI!C23+CL_no_gold_plat!C31+EF!C5+WC!C25)/1000000 -> 265.76041 | D5: =SUM(BI!D23+CL_no_gold_plat!D31+EF!D5+WC!D25)/1000000 -> 272.39229 | E5: =SUM(BI!E23+CL_no_gold_plat!E31+EF!E5+WC!E25)/1000000 -> 279.38872 | F5: =SUM(BI!F23+CL_no_gold_plat!F31+EF!F5+WC!F25)/1000000 -> 286.57311 | G5: =SUM(BI!G23+CL_no_gold_plat!G31+EF!G5+WC!G25)/1000000 -> 293.84803 | H5: =SUM(BI!H23+CL_no_gold_plat!H31+EF!H5+WC!H25)/1000000 -> 301.21726 | I5: =SUM(BI!I23+CL_no_gold_plat!I31+EF!I5+WC!I25)/1000000 -> 308.73678 | ... K5: =SUM(BI!K23+CL_no_gold_plat!K31+EF!K5+WC!K25)/1000000 -> 324.40442
A6: operating_expenses | B6: =SUM(BI!B24+CL_no_gold_plat!B32+EF!B6+WC!B26)/1000000 -> 129.10682 | C6: =SUM(BI!C24+CL_no_gold_plat!C32+EF!C6+WC!C26)/1000000 -> 132.1632 | D6: =SUM(BI!D24+CL_no_gold_plat!D32+EF!D6+WC!D26)/1000000 -> 135.46125 | E6: =SUM(BI!E24+CL_no_gold_plat!E32+EF!E6+WC!E26)/1000000 -> 138.94059 | F6: =SUM(BI!F24+CL_no_gold_plat!F32+EF!F6+WC!F26)/1000000 -> 142.5134 | G6: =SUM(BI!G24+CL_no_gold_plat!G32+EF!G6+WC!G26)/1000000 -> 146.13123 | H6: =SUM(BI!H24+CL_no_gold_plat!H32+EF!H6+WC!H26)/1000000 -> 149.79597 | I6: =SUM(BI!I24+CL_no_gold_plat!I32+EF!I6+WC!I26)/1000000 -> 153.53544 | ... K6: =SUM(BI!K24+CL_no_gold_plat!K32+EF!K6+WC!K26)/1000000 -> 161.32699
A7: operating_income | B7: =SUM(BI!B25+CL_no_gold_plat!B33+EF!B7+WC!B27)/1000000 -> 125.3374 | C7: =SUM(BI!C25+CL_no_gold_plat!C33+EF!C7+WC!C27)/1000000 -> 128.30454 | D7: =SUM(BI!D25+CL_no_gold_plat!D33+EF!D7+WC!D27)/1000000 -> 131.5063 | E7: =SUM(BI!E25+CL_no_gold_plat!E33+EF!E7+WC!E27)/1000000 -> 134.88406 | F7: =SUM(BI!F25+CL_no_gold_plat!F33+EF!F7+WC!F27)/1000000 -> 138.35255 | G7: =SUM(BI!G25+CL_no_gold_plat!G33+EF!G7+WC!G27)/1000000 -> 141.86476 | H7: =SUM(BI!H25+CL_no_gold_plat!H33+EF!H7+WC!H27)/1000000 -> 145.4225 | I7: =SUM(BI!I25+CL_no_gold_plat!I33+EF!I7+WC!I27)/1000000 -> 149.05279 | ... K7: =SUM(BI!K25+CL_no_gold_plat!K33+EF!K7+WC!K27)/1000000 -> 156.61686
A8: net_income | B8: =SUM(BI!B26+CL_no_gold_plat!B34+EF!B8+WC!B28)/1000000 -> 92.87425 | C8: =SUM(BI!C26+CL_no_gold_plat!C34+EF!C8+WC!C28)/1000000 -> 95.072886 | D8: =SUM(BI!D26+CL_no_gold_plat!D34+EF!D8+WC!D28)/1000000 -> 97.445367 | E8: =SUM(BI!E26+CL_no_gold_plat!E34+EF!E8+WC!E28)/1000000 -> 99.948265 | F8: =SUM(BI!F26+CL_no_gold_plat!F34+EF!F8+WC!F28)/1000000 -> 102.5184 | G8: =SUM(BI!G26+CL_no_gold_plat!G34+EF!G8+WC!G28)/1000000 -> 105.12092 | H8: =SUM(BI!H26+CL_no_gold_plat!H34+EF!H8+WC!H28)/1000000 -> 107.75719 | I8: =SUM(BI!I26+CL_no_gold_plat!I34+EF!I8+WC!I28)/1000000 -> 110.44721 | ... K8: =SUM(BI!K26+CL_no_gold_plat!K34+EF!K8+WC!K28)/1000000 -> 116.05214
A9: discount_factor | B9: =SUM(BI!B27+CL_no_gold_plat!B35+EF!B9+WC!B29) -> 0.953719 | C9: =SUM(BI!C27+CL_no_gold_plat!C35+EF!C9+WC!C29) -> 0.91531276 | D9: =SUM(BI!D27+CL_no_gold_plat!D35+EF!D9+WC!D29) -> 0.88171691 | E9: =SUM(BI!E27+CL_no_gold_plat!E35+EF!E9+WC!E29) -> 0.85121156 | F9: =SUM(BI!F27+CL_no_gold_plat!F35+EF!F9+WC!F29) -> 0.82281839 | G9: =SUM(BI!G27+CL_no_gold_plat!G35+EF!G9+WC!G29) -> 0.79597349 | H9: =SUM(BI!H27+CL_no_gold_plat!H35+EF!H9+WC!H29) -> 0.77034637 | I9: =SUM(BI!I27+CL_no_gold_plat!I35+EF!I9+WC!I29) -> 0.74573885 | ... K9: =SUM(BI!K27+CL_no_gold_plat!K35+EF!K9+WC!K29) -> 0.69913397
A10: pv_premium | B10: =SUM(BI!B28+CL_no_gold_plat!B36+EF!B10+WC!B30)/1000000 -> 410.43877 | C10: =SUM(BI!C28+CL_no_gold_plat!C36+EF!C10+WC!C30)/1000000 -> 403.23555 | D10: =SUM(BI!D28+CL_no_gold_plat!D36+EF!D10+WC!D30)/1000000 -> 398.12824 | E10: =SUM(BI!E28+CL_no_gold_plat!E36+EF!E10+WC!E30)/1000000 -> 394.22612 | F10: =SUM(BI!F28+CL_no_gold_plat!F36+EF!F10+WC!F30)/1000000 -> 390.87548 | G10: =SUM(BI!G28+CL_no_gold_plat!G36+EF!G10+WC!G30)/1000000 -> 387.72195 | H10: =SUM(BI!H28+CL_no_gold_plat!H36+EF!H10+WC!H30)/1000000 -> 384.64926 | I10: =SUM(BI!I28+CL_no_gold_plat!I36+EF!I10+WC!I30)/1000000 -> 381.6578 | ... K10: =SUM(BI!K28+CL_no_gold_plat!K36+EF!K10+WC!K30)/1000000 -> 375.96393
A11: pv_loss | B11: =SUM(BI!B29+CL_no_gold_plat!B37+EF!B11+WC!B31)/1000000 -> 247.59927 | C11: =SUM(BI!C29+CL_no_gold_plat!C37+EF!C11+WC!C31)/1000000 -> 243.2539 | D11: =SUM(BI!D29+CL_no_gold_plat!D37+EF!D11+WC!D31)/1000000 -> 240.17289 | E11: =SUM(BI!E29+CL_no_gold_plat!E37+EF!E11+WC!E31)/1000000 -> 237.81891 | F11: =SUM(BI!F29+CL_no_gold_plat!F37+EF!F11+WC!F31)/1000000 -> 235.79762 | G11: =SUM(BI!G29+CL_no_gold_plat!G37+EF!G11+WC!G31)/1000000 -> 233.89524 | H11: =SUM(BI!H29+CL_no_gold_plat!H37+EF!H11+WC!H31)/1000000 -> 232.04162 | I11: =SUM(BI!I29+CL_no_gold_plat!I37+EF!I11+WC!I31)/1000000 -> 230.23701 | ... K11: =SUM(BI!K29+CL_no_gold_plat!K37+EF!K11+WC!K31)/1000000 -> 226.80215
A12: pv_expense | B12: =B6*B9 -> 123.13163 | C12: =C6*C9 -> 120.97067 | D12: =D6*D9 -> 119.43847 | E12: =E6*E9 -> 118.26784 | F12: =F6*F9 -> 117.26264 | G12: =G6*G9 -> 116.31659 | H12: =H6*H9 -> 115.39478 | I12: =I6*I9 -> 114.49734 | ... K12: =K6*K9 -> 112.78918
A13: pv_net_income | B13: =B8*B9 -> 88.575937 | C13: =C8*C9 -> 87.021426 | D13: =D8*D9 -> 85.919228 | E13: =E8*E9 -> 85.077119 | F13: =F8*F9 -> 84.354025 | G13: =G8*G9 -> 83.673468 | H13: =H8*H9 -> 83.010357 | I13: =I8*I9 -> 82.364775 | ... K13: =K8*K9 -> 81.135994

Sheet BI
A1: year | B1: 2175 | C1: 2176 | D1: 2177 | E1: 2178 | F1: 2179 | G1: 2180 | H1: 2181 | I1: 2182 | J1: 2183 | K1: 2184
A2: inflation | B2: 0.022825428 | C2: 0.023673261 | D2: 0.024954336 | E2: 0.025685141 | F2: 0.025714643 | G2: 0.025385925 | H2: 0.025078383 | I2: 0.024963757 | J2: 0.02501092 | K2: 0.025108676
A3: risk_free_rate | B3: 0.048526873 | C3: 0.041959693 | D3: 0.038102759 | E3: 0.035837566 | F3: 0.034507207 | G3: 0.033725882 | H3: 0.033267006 | I3: 0.032997507 | J3: 0.032839228 | K3: 0.032746271
A4: premium_forecast | B4: 4.5187965e+09 | C4: 4.6257712e+09 | D4: 4.7412042e+09 | E4: 4.8629827e+09 | F4: 4.9880326e+09 | G4: 5.1146584e+09 | H4: 5.2429258e+09 | I4: 5.3738089e+09 | J4: 5.5082128e+09 | K4: 5.6465168e+09
A5: loss_forecast | B5: 2.7127555e+09 | C5: 2.7769753e+09 | D5: 2.8462729e+09 | E5: 2.9193798e+09 | F5: 2.9944506e+09 | G5: 3.0704675e+09 | H5: 3.1474699e+09 | I5: 3.2260425e+09 | J5: 3.3067288e+09 | K5: 3.3897564e+09
A6: operating_expenses | B6: 1.355639e+09 | C6: 1.3877314e+09 | D6: 1.4223613e+09 | E6: 1.4588948e+09 | F6: 1.4964098e+09 | G6: 1.5343975e+09 | H6: 1.5728777e+09 | I6: 1.6121427e+09 | J6: 1.6524638e+09 | K6: 1.693955e+09
A7: operating_income | B7: 1.3160595e+09 | C7: 1.3472149e+09 | D7: 1.3808338e+09 | E7: 1.4163007e+09 | F7: 1.4527203e+09 | G7: 1.489599e+09 | H7: 1.5269557e+09 | I7: 1.5650743e+09 | J7: 1.6042182e+09 | K7: 1.644498e+09
A8: net_income | B8: 9.7519208e+08 | C8: 9.9827806e+08 | D8: 1.0231894e+09 | E8: 1.0494702e+09 | F8: 1.0764569e+09 | G8: 1.1037838e+09 | H8: 1.1314649e+09 | I8: 1.1597105e+09 | J8: 1.188716e+09 | K8: 1.218563e+09
A9: discount_factor | B9: 0.953719 | C9: 0.91531276 | D9: 0.88171691 | E9: 0.85121156 | F9: 0.82281839 | G9: 0.79597349 | H9: 0.77034637 | I9: 0.74573885 | J9: 0.722028 | K9: 0.69913397
A10: pv_premium | B10: 4.3096621e+09 | C10: 4.2340274e+09 | D10: 4.1804e+09 | E10: 4.1394271e+09 | F10: 4.104245e+09 | G10: 4.0711325e+09 | H10: 4.0388688e+09 | I10: 4.0074581e+09 | J10: 3.9770839e+09 | K10: 3.9476717e+09
A11: pv_loss | B11: 2.5872065e+09 | C11: 2.5418009e+09 | D11: 2.5096069e+09 | E11: 2.4850098e+09 | F11: 2.463889e+09 | G11: 2.4440107e+09 | H11: 2.424642e+09 | I11: 2.4057852e+09 | J11: 2.3875508e+09 | K11: 2.3698939e+09
A12: pv_expense | B12: 1.2928986e+09 | C12: 1.2702082e+09 | D12: 1.25412e+09 | E12: 1.2418281e+09 | F12: 1.2312735e+09 | G12: 1.2213398e+09 | H12: 1.2116607e+09 | I12: 1.2022374e+09 | J12: 1.1931252e+09 | K12: 1.1843015e+09
A13: pv_net_income | B13: 9.3005922e+08 | C13: 9.1373664e+08 | D13: 9.0216342e+08 | E13: 8.9332116e+08 | F13: 8.8572857e+08 | G13: 8.7858264e+08 | H13: 8.7161989e+08 | I13: 8.6484119e+08 | J13: 8.5828621e+08 | K13: 8.5193882e+08

Sheet CL_no_gold_plat
A1: year | B1: 2175 | C1: 2176 | D1: 2177 | E1: 2178 | F1: 2179 | G1: 2180 | H1: 2181 | I1: 2182 | J1: 2183 | K1: 2184
A2: inflation | B2: 0.022825428 | C2: 0.023673261 | D2: 0.024954336 | E2: 0.025685141 | F2: 0.025714643 | G2: 0.025385925 | H2: 0.025078383 | I2: 0.024963757 | J2: 0.02501092 | K2: 0.025108676
A3: risk_free_rate | B3: 0.048526873 | C3: 0.041959693 | D3: 0.038102759 | E3: 0.035837566 | F3: 0.034507207 | G3: 0.033725882 | H3: 0.033267006 | I3: 0.032997507 | J3: 0.032839228 | K3: 0.032746271
A4: premium_forecast | B4: 2.6222226e+10 | C4: 2.6842991e+10 | D4: 2.751284e+10 | E4: 2.8219512e+10 | F4: 2.8945166e+10 | G4: 2.9679966e+10 | H4: 3.0424292e+10 | I4: 3.1183796e+10 | J4: 3.1963732e+10 | K4: 3.2766299e+10
A5: loss_forecast | B5: 1.5733335e+10 | C5: 1.6105795e+10 | D5: 1.6507704e+10 | E5: 1.6931707e+10 | F5: 1.73671e+10 | G5: 1.780798e+10 | H5: 1.8254575e+10 | I5: 1.8710278e+10 | J5: 1.9178239e+10 | K5: 1.9659779e+10
A6: operating_expenses | B6: 7.8666677e+09 | C6: 8.0528974e+09 | D6: 8.2538521e+09 | E6: 8.4658535e+09 | F6: 8.6835499e+09 | G6: 8.9039898e+09 | H6: 9.1272875e+09 | I6: 9.3551389e+09 | J6: 9.5891195e+09 | K6: 9.8298896e+09
A7: operating_income | B7: 7.6369911e+09 | C7: 7.8177836e+09 | D7: 8.0128712e+09 | E7: 8.2186829e+09 | F7: 8.4300234e+09 | G7: 8.6440273e+09 | H7: 8.8608056e+09 | I7: 9.0820046e+09 | J7: 9.3091539e+09 | K7: 9.5428944e+09
A8: net_income | B8: 5.658964e+09 | C8: 5.7929301e+09 | D8: 5.9374889e+09 | E8: 6.0899941e+09 | F8: 6.2465961e+09 | G8: 6.4051717e+09 | H8: 6.5658031e+09 | I8: 6.7297102e+09 | J8: 6.8980265e+09 | K8: 7.0712268e+09
A9: discount_factor | B9: 0.953719 | C9: 0.91531276 | D9: 0.88171691 | E9: 0.85121156 | F9: 0.82281839 | G9: 0.79597349 | H9: 0.77034637 | I9: 0.74573885 | J9: 0.722028 | K9: 0.69913397
A10: pv_premium | B10: 2.5008635e+10 | C10: 2.4569732e+10 | D10: 2.4258537e+10 | E10: 2.4020774e+10 | F10: 2.3816615e+10 | G10: 2.3624466e+10 | H10: 2.3437243e+10 | I10: 2.3254968e+10 | J10: 2.3078709e+10 | K10: 2.2908033e+10
A11: pv_loss | B11: 1.5005181e+10 | C11: 1.4741839e+10 | D11: 1.4555122e+10 | E11: 1.4412465e+10 | F11: 1.4289969e+10 | G11: 1.417468e+10 | H11: 1.4062346e+10 | I11: 1.3952981e+10 | J11: 1.3847226e+10 | K11: 1.374482e+10
A12: pv_expense | B12: 7.5025905e+09 | C12: 7.3709197e+09 | D12: 7.277561e+09 | E12: 7.2062323e+09 | F12: 7.1449846e+09 | G12: 7.0873398e+09 | H12: 7.0311728e+09 | I12: 6.9764905e+09 | J12: 6.9236128e+09 | K12: 6.8724098e+09
A13: pv_net_income | B13: 5.3970615e+09 | C13: 5.3023429e+09 | D13: 5.2351843e+09 | E13: 5.1838734e+09 | F13: 5.1398142e+09 | G13: 5.0983469e+09 | H13: 5.0579426e+09 | I13: 5.0186063e+09 | J13: 4.9805683e+09 | K13: 4.9437349e+09

Sheet EF
A1: year | B1: 2175 | C1: 2176 | D1: 2177 | E1: 2178 | F1: 2179 | G1: 2180 | H1: 2181 | I1: 2182 | J1: 2183 | K1: 2184
A2: inflation | B2: 0.022825428 | C2: 0.023673261 | D2: 0.024954336 | E2: 0.025685141 | F2: 0.025714643 | G2: 0.025385925 | H2: 0.025078383 | I2: 0.024963757 | J2: 0.02501092 | K2: 0.025108676
A3: risk_free_rate | B3: 0.048526873 | C3: 0.041959693 | D3: 0.038102759 | E3: 0.035837566 | F3: 0.034507207 | G3: 0.033725882 | H3: 0.033267006 | I3: 0.032997507 | J3: 0.032839228 | K3: 0.032746271
A4: premium_forecast | B4: 4.3035608e+08 | C4: 4.4054401e+08 | D4: 4.5153749e+08 | E4: 4.631353e+08 | F4: 4.7504466e+08 | G4: 4.871041e+08 | H4: 4.9931989e+08 | I4: 5.1178479e+08 | J4: 5.24585e+08 | K4: 5.3775663e+08
A5: loss_forecast | B5: 2.5961449e+08 | C5: 2.6576041e+08 | D5: 2.7239229e+08 | E5: 2.7938872e+08 | F5: 2.8657311e+08 | G5: 2.9384803e+08 | H5: 3.0121726e+08 | I5: 3.0873678e+08 | J5: 3.1645857e+08 | K5: 3.2440442e+08
A6: operating_expenses | B6: 1.2910682e+08 | C6: 1.321632e+08 | D6: 1.3546125e+08 | E6: 1.3894059e+08 | F6: 1.425134e+08 | G6: 1.4613123e+08 | H6: 1.4979597e+08 | I6: 1.5353544e+08 | J6: 1.573755e+08 | K6: 1.6132699e+08
A7: operating_income | B7: 1.253374e+08 | C7: 1.2830454e+08 | D7: 1.315063e+08 | E7: 1.3488406e+08 | F7: 1.3835255e+08 | G7: 1.4186476e+08 | H7: 1.454225e+08 | I7: 1.4905279e+08 | J7: 1.5278074e+08 | K7: 1.5661686e+08
A8: net_income | B8: 92874250 | C8: 95072886 | D8: 97445367 | E8: 99948265 | F8: 1.025184e+08 | G8: 1.0512092e+08 | H8: 1.0775719e+08 | I8: 1.1044721e+08 | J8: 1.132096e+08 | K8: 1.1605214e+08
A9: discount_factor | B9: 0.953719 | C9: 0.91531276 | D9: 0.88171691 | E9: 0.85121156 | F9: 0.82281839 | G9: 0.79597349 | H9: 0.77034637 | I9: 0.74573885 | J9: 0.722028 | K9: 0.69913397
A10: pv_premium | B10: 4.1043877e+08 | C10: 4.0323555e+08 | D10: 3.9812824e+08 | E10: 3.9422612e+08 | F10: 3.9087548e+08 | G10: 3.8772195e+08 | H10: 3.8464926e+08 | I10: 3.816578e+08 | J10: 3.7876506e+08 | K10: 3.7596393e+08
A11: pv_loss | B11: 2.4759927e+08 | C11: 2.432539e+08 | D11: 2.4017289e+08 | E11: 2.3781891e+08 | F11: 2.3579762e+08 | G11: 2.3389524e+08 | H11: 2.3204162e+08 | I11: 2.3023701e+08 | J11: 2.2849195e+08 | K11: 2.2680215e+08
A12: pv_expense | B12: 1.2313163e+08 | C12: 1.2097067e+08 | D12: 1.1943847e+08 | E12: 1.1826784e+08 | F12: 1.1726264e+08 | G12: 1.1631659e+08 | H12: 1.1539478e+08 | I12: 1.1449734e+08 | J12: 1.1362952e+08 | K12: 1.1278918e+08
A13: pv_net_income | B13: 88575937 | C13: 87021426 | D13: 85919228 | E13: 85077119 | F13: 84354025 | G13: 83673468 | H13: 83010357 | I13: 82364775 | J13: 81740499 | K13: 81135994

Sheet WC
A1: year | B1: 2175 | C1: 2176 | D1: 2177 | E1: 2178 | F1: 2179 | G1: 2180 | H1: 2181 | I1: 2182 | J1: 2183 | K1: 2184
A2: inflation | B2: 0.022825428 | C2: 0.023673261 | D2: 0.024954336 | E2: 0.025685141 | F2: 0.025714643 | G2: 0.025385925 | H2: 0.025078383 | I2: 0.024963757 | J2: 0.02501092 | K2: 0.025108676
A3: risk_free_rate | B3: 0.048526873 | C3: 0.041959693 | D3: 0.038102759 | E3: 0.035837566 | F3: 0.034507207 | G3: 0.033725882 | H3: 0.033267006 | I3: 0.032997507 | J3: 0.032839228 | K3: 0.032746271
A4: premium_forecast | B4: 25420773 | C4: 26022566 | D4: 26671941 | E4: 27357014 | F4: 28060490 | G4: 28772831 | H4: 29494407 | I4: 30230699 | J4: 30986796 | K4: 31764834
A5: loss_forecast | B5: 15252464 | C5: 15613539 | D5: 16003165 | E5: 16414208 | F5: 16836294 | G5: 17263699 | H5: 17696644 | I5: 18138419 | J5: 18592078 | K5: 19058900
A6: operating_expenses | B6: 7626231.9 | C6: 7806769.7 | D6: 8001582.4 | E6: 8207104.2 | F6: 8418146.9 | G6: 8631849.4 | H6: 8848322.2 | I6: 9069209.6 | J6: 9296038.8 | K6: 9529450.1
A7: operating_income | B7: 7403575 | C7: 7578841.8 | D7: 7767966.8 | E7: 7967488.1 | F7: 8172369.2 | G7: 8379832.4 | H7: 8589985 | I7: 8804423.3 | J7: 9024630 | K7: 9251226.5
A8: net_income | B8: 5486004.1 | C8: 5615875.7 | D8: 5756016.2 | E8: 5903860.3 | F8: 6055675.9 | G8: 6209404.9 | H8: 6365126.7 | I8: 6524024.2 | J8: 6687196 | K8: 6855102.7
A9: discount_factor | B9: 0.953719 | C9: 0.91531276 | D9: 0.88171691 | E9: 0.85121156 | F9: 0.82281839 | G9: 0.79597349 | H9: 0.77034637 | I9: 0.74573885 | J9: 0.722028 | K9: 0.69913397
A10: pv_premium | B10: 24244274 | C10: 23818786 | D10: 23517102 | E10: 23286606 | F10: 23088687 | G10: 22902411 | H10: 22720910 | I10: 22544206 | J10: 22373335 | K10: 22207874
A11: pv_loss | B11: 14546564 | C11: 14291272 | D11: 14110261 | E11: 13971964 | F11: 13853212 | G11: 13741446 | H11: 13632546 | I11: 13526524 | J11: 13424001 | K11: 13324725
A12: pv_expense | B12: 7273282.2 | C12: 7145635.8 | D12: 7055130.5 | E12: 6985981.9 | F12: 6926606.1 | G12: 6870723.2 | H12: 6816272.9 | I12: 6763261.9 | J12: 6712000.4 | K12: 6662362.3
A13: pv_net_income | B13: 5232106.4 | C13: 5140282.7 | D13: 5075176.8 | E13: 5025434.1 | F13: 4982721.6 | G13: 4942521.6 | H13: 4903352.2 | I13: 4865218.3 | J13: 4828342.8 | K13: 4792635.2
